[{"family":"MaterialIcons","fonts":[{"asset":"fonts/MaterialIcons-Regular.otf"}]},{"family":"Camelia","fonts":[{"weight":700,"asset":"fonts/RNSCamelia-Bold.otf"},{"weight":500,"asset":"fonts/RNSCamelia-Medium.otf"},{"weight":400,"asset":"fonts/RNSCamelia-Regular.otf"}]},{"family":"Nunito","fonts":[{"weight":700,"asset":"fonts/Nunito-Bold.ttf"},{"weight":500,"asset":"fonts/Nunito-Medium.ttf"},{"weight":400,"asset":"fonts/Nunito-Regular.ttf"}]},{"family":"packages/cupertino_icons/CupertinoIcons","fonts":[{"asset":"packages/cupertino_icons/assets/CupertinoIcons.ttf"}]}]